[
    {
        "DEFENSOR": "Ademilson Navarrete Linhares",
        "SUBS\u00cdDIO": 36127.4,
        "TETO": 12042.46667,
        "ACUMULO MESES ANTERIORES - 1058": 802.8266667,
        "DESCONTO SEM ACUMULA\u00c7\u00c3O ATUAL - 1045": "sem info",
        "FIXA": 0.0,
        "F\u00c9RIAS": 0.0,
        "DESCONTOS MES ANTERIOR ": 0,
        "TOTAL": 0.0,
        "STATUS": "PAGA TOTAL",
        "TOTAL A PAGAR - 1056": 0.0,
        "valor pago - folha normal": "sem info",
        "LAN\u00c7AMENTO": "OK",
        "valor a lan\u00e7ar em complementar": "sem info",
        "BANCO": "CAIXA",
        "PORTARIA FIXA": "sem info",
        "PORTARIA F\u00c9RIAS": "sem info"
    },
    {
        "DEFENSOR": "Adriana Da Silva Rodrigues",
        "SUBS\u00cdDIO": 36127.4,
        "TETO": 12042.46667,
        "ACUMULO MESES ANTERIORES - 1058": 0.0,
        "DESCONTO SEM ACUMULA\u00c7\u00c3O ATUAL - 1045": "sem info",
        "FIXA": 7626.895556,
        "F\u00c9RIAS": 4014.155556,
        "DESCONTOS MES ANTERIOR ": 0,
        "TOTAL": 11641.05111,
        "STATUS": "PAGA TOTAL",
        "TOTAL A PAGAR - 1056": 11641.05111,
        "valor pago - folha normal": 10436.8,
        "LAN\u00c7AMENTO": "OK",
        "valor a lan\u00e7ar em complementar": 1204.251111,
        "BANCO": "BANCO DO BRASIL",
        "PORTARIA FIXA": "PORTARIA N\u00ba 1274/2022/SDPG",
        "PORTARIA F\u00c9RIAS": "ART. 33 DA PORTARIA N\u00ba 182/2023"
    },
    {
        "DEFENSOR": "Air Praeiro Alves",
        "SUBS\u00cdDIO": 36127.4,
        "TETO": 12042.46667,
        "ACUMULO MESES ANTERIORES - 1058": 0.0,
        "DESCONTO SEM ACUMULA\u00c7\u00c3O ATUAL - 1045": 150.0,
        "FIXA": 0.0,
        "F\u00c9RIAS": 0.0,
        "DESCONTOS MES ANTERIOR ": 0,
        "TOTAL": 0.0,
        "STATUS": "PAGA TOTAL",
        "TOTAL A PAGAR - 1056": 0.0,
        "valor pago - folha normal": "sem info",
        "LAN\u00c7AMENTO": "ZERADO",
        "valor a lan\u00e7ar em complementar": "sem info",
        "BANCO": "BANCO DO BRASIL",
        "PORTARIA FIXA": "sem info",
        "PORTARIA F\u00c9RIAS": "sem info"
    }
]